observability/__init__.py
observability/core.py
observability/logger.py
observability/metrics.py
observability/tracer.py
astra_observability-0.1.0.dist-info/METADATA
astra_observability-0.1.0.dist-info/WHEEL
astra_observability-0.1.0.dist-info/licenses/LICENSE
astra_observability-0.1.0.dist-info/RECORD
