Metadata-Version: 2.4
Name: astra-observability
Version: 0.1.0
Summary: Astra Observability - Tracing, metrics, and structured logging for AI agents
Project-URL: Homepage, https://github.com/HeeManSu/astra-agi
Project-URL: Repository, https://github.com/HeeManSu/astra-agi
Project-URL: Issues, https://github.com/HeeManSu/astra-agi/issues
Author-email: Himanshu Sharma <himanshu.kumarr07@gmail.com>
License: MIT
License-File: LICENSE
Keywords: ai-agents,logging,metrics,observability,opentelemetry,tracing
Classifier: Development Status :: 4 - Beta
Classifier: Intended Audience :: Developers
Classifier: License :: OSI Approved :: MIT License
Classifier: Programming Language :: Python :: 3
Classifier: Programming Language :: Python :: 3.10
Classifier: Programming Language :: Python :: 3.11
Classifier: Programming Language :: Python :: 3.12
Classifier: Programming Language :: Python :: 3.13
Classifier: Topic :: System :: Monitoring
Requires-Python: <3.14,>=3.10
Requires-Dist: loguru>=0.7.0
Requires-Dist: opentelemetry-api>=1.20.0
Requires-Dist: opentelemetry-sdk>=1.20.0
Requires-Dist: prometheus-client>=0.20.0
